{
  "BNB": [
    {
      "price": 634.68,
      "volume": 981720836
    },
    {
      "price": 634.68,
      "volume": 981720836
    }
  ],
  "XRP": [
    {
      "price": 1.38,
      "volume": 2009215807
    },
    {
      "price": 1.38,
      "volume": 2009215807
    }
  ],
  "SOL": [
    {
      "price": 88.88,
      "volume": 3553165279
    },
    {
      "price": 88.88,
      "volume": 3553165279
    }
  ],
  "TRX": [
    {
      "price": 0.314767,
      "volume": 501826831
    },
    {
      "price": 0.314767,
      "volume": 501826831
    }
  ],
  "FIGR_HELOC": [
    {
      "price": 1.024,
      "volume": 27941743
    },
    {
      "price": 1.024,
      "volume": 27941743
    }
  ],
  "DOGE": [
    {
      "price": 0.092615,
      "volume": 1079985927
    },
    {
      "price": 0.092615,
      "volume": 1079985927
    }
  ],
  "USDS": [
    {
      "price": 0.999925,
      "volume": 35245919
    },
    {
      "price": 0.999925,
      "volume": 35245919
    }
  ],
  "WBT": [
    {
      "price": 54.01,
      "volume": 54485608
    },
    {
      "price": 54.01,
      "volume": 54485608
    }
  ],
  "ADA": [
    {
      "price": 0.261038,
      "volume": 435946682
    },
    {
      "price": 0.261038,
      "volume": 435946682
    }
  ],
  "BCH": [
    {
      "price": 466.86,
      "volume": 190053466
    },
    {
      "price": 466.86,
      "volume": 190053466
    }
  ],
  "HYPE": [
    {
      "price": 39.08,
      "volume": 273820840
    },
    {
      "price": 39.08,
      "volume": 273820840
    }
  ],
  "LEO": [
    {
      "price": 9.51,
      "volume": 407503
    },
    {
      "price": 9.51,
      "volume": 407503
    }
  ],
  "LINK": [
    {
      "price": 9.1,
      "volume": 337885888
    },
    {
      "price": 9.1,
      "volume": 337885888
    }
  ],
  "XMR": [
    {
      "price": 334.42,
      "volume": 105607010
    },
    {
      "price": 334.42,
      "volume": 105607010
    }
  ],
  "USDE": [
    {
      "price": 0.999237,
      "volume": 78056996
    },
    {
      "price": 0.999237,
      "volume": 78056996
    }
  ],
  "XLM": [
    {
      "price": 0.174071,
      "volume": 143905674
    },
    {
      "price": 0.174071,
      "volume": 143905674
    }
  ],
  "CC": [
    {
      "price": 0.140823,
      "volume": 12069728
    },
    {
      "price": 0.140823,
      "volume": 12069728
    }
  ],
  "USD1": [
    {
      "price": 0.999484,
      "volume": 1074058528
    },
    {
      "price": 0.999484,
      "volume": 1074058528
    }
  ],
  "DAI": [
    {
      "price": 0.999855,
      "volume": 147528170
    },
    {
      "price": 0.999855,
      "volume": 147528170
    }
  ],
  "LTC": [
    {
      "price": 55.24,
      "volume": 333519043
    },
    {
      "price": 55.24,
      "volume": 333519043
    }
  ],
  "M": [
    {
      "price": 2.4,
      "volume": 29102205
    },
    {
      "price": 2.4,
      "volume": 29102205
    }
  ],
  "RAIN": [
    {
      "price": 0.00863398,
      "volume": 56935274
    },
    {
      "price": 0.00863398,
      "volume": 56935274
    }
  ],
  "AVAX": [
    {
      "price": 9.43,
      "volume": 225633741
    },
    {
      "price": 9.43,
      "volume": 225633741
    }
  ],
  "HBAR": [
    {
      "price": 0.091848,
      "volume": 87105129
    },
    {
      "price": 0.091848,
      "volume": 87105129
    }
  ],
  "PYUSD": [
    {
      "price": 0.99998,
      "volume": 104203973
    },
    {
      "price": 0.99998,
      "volume": 104203973
    }
  ],
  "ZEC": [
    {
      "price": 225.72,
      "volume": 314978443
    },
    {
      "price": 225.72,
      "volume": 314978443
    }
  ],
  "SUI": [
    {
      "price": 0.940112,
      "volume": 346038919
    },
    {
      "price": 0.940112,
      "volume": 346038919
    }
  ],
  "SHIB": [
    {
      "price": 0.00000596,
      "volume": 113136458
    },
    {
      "price": 0.00000596,
      "volume": 113136458
    }
  ],
  "TAO": [
    {
      "price": 341.01,
      "volume": 977142350
    },
    {
      "price": 341.01,
      "volume": 977142350
    }
  ],
  "TON": [
    {
      "price": 1.31,
      "volume": 74796073
    },
    {
      "price": 1.31,
      "volume": 74796073
    }
  ],
  "CRO": [
    {
      "price": 0.074234,
      "volume": 8691485
    },
    {
      "price": 0.074234,
      "volume": 8691485
    }
  ],
  "WLFI": [
    {
      "price": 0.099943,
      "volume": 60730461
    },
    {
      "price": 0.099943,
      "volume": 60730461
    }
  ],
  "XAUT": [
    {
      "price": 4451.74,
      "volume": 687665847
    },
    {
      "price": 4451.74,
      "volume": 687665847
    }
  ],
  "USYC": [
    {
      "price": 1.12,
      "volume": 2159.66
    },
    {
      "price": 1.12,
      "volume": 2159.66
    }
  ],
  "MNT": [
    {
      "price": 0.710021,
      "volume": 52057580
    },
    {
      "price": 0.710021,
      "volume": 52057580
    }
  ],
  "PAXG": [
    {
      "price": 4456.08,
      "volume": 379865973
    },
    {
      "price": 4456.08,
      "volume": 379865973
    }
  ],
  "UNI": [
    {
      "price": 3.61,
      "volume": 219785452
    },
    {
      "price": 3.61,
      "volume": 219785452
    }
  ],
  "DOT": [
    {
      "price": 1.33,
      "volume": 203980841
    },
    {
      "price": 1.33,
      "volume": 203980841
    }
  ],
  "BUIDL": [
    {
      "price": 1,
      "volume": 0
    },
    {
      "price": 1,
      "volume": 0
    }
  ],
  "PI": [
    {
      "price": 0.18829,
      "volume": 17510614
    },
    {
      "price": 0.18829,
      "volume": 17510614
    }
  ],
  "USDG": [
    {
      "price": 0.999862,
      "volume": 53589943
    },
    {
      "price": 0.999862,
      "volume": 53589943
    }
  ],
  "OKB": [
    {
      "price": 85.37,
      "volume": 15568628
    },
    {
      "price": 85.37,
      "volume": 15568628
    }
  ],
  "USDF": [
    {
      "price": 0.998458,
      "volume": 775171
    },
    {
      "price": 0.998458,
      "volume": 775171
    }
  ],
  "SKY": [
    {
      "price": 0.072965,
      "volume": 16080366
    },
    {
      "price": 0.072965,
      "volume": 16080366
    }
  ],
  "AAVE": [
    {
      "price": 108.18,
      "volume": 316820276
    },
    {
      "price": 108.18,
      "volume": 316820276
    }
  ],
  "ASTER": [
    {
      "price": 0.661654,
      "volume": 123103599
    },
    {
      "price": 0.661654,
      "volume": 123103599
    }
  ],
  "NEAR": [
    {
      "price": 1.23,
      "volume": 187365040
    },
    {
      "price": 1.23,
      "volume": 187365040
    }
  ],
  "HTX": [
    {
      "price": 0.00000171,
      "volume": 10991197
    },
    {
      "price": 0.00000171,
      "volume": 10991197
    }
  ],
  "PEPE": [
    {
      "price": 0.00000345,
      "volume": 261725957
    },
    {
      "price": 0.00000345,
      "volume": 261725957
    }
  ],
  "RLUSD": [
    {
      "price": 0.999735,
      "volume": 158545918
    },
    {
      "price": 0.999735,
      "volume": 158545918
    }
  ],
  "BGB": [
    {
      "price": 2.03,
      "volume": 20231252
    },
    {
      "price": 2.03,
      "volume": 20231252
    }
  ],
  "SIREN": [
    {
      "price": 1.92,
      "volume": 68933177
    },
    {
      "price": 1.92,
      "volume": 68933177
    }
  ],
  "ETC": [
    {
      "price": 8.46,
      "volume": 43878941
    },
    {
      "price": 8.46,
      "volume": 43878941
    }
  ],
  "BFUSD": [
    {
      "price": 0.998904,
      "volume": 1366933
    },
    {
      "price": 0.998904,
      "volume": 1366933
    }
  ],
  "USDY": [
    {
      "price": 1.12,
      "volume": 651039
    },
    {
      "price": 1.12,
      "volume": 651039
    }
  ],
  "ICP": [
    {
      "price": 2.35,
      "volume": 51590553
    },
    {
      "price": 2.35,
      "volume": 51590553
    }
  ],
  "ONDO": [
    {
      "price": 0.263507,
      "volume": 91992134
    },
    {
      "price": 0.263507,
      "volume": 91992134
    }
  ],
  "GT": [
    {
      "price": 6.68,
      "volume": 1554445
    },
    {
      "price": 6.68,
      "volume": 1554445
    }
  ],
  "QNT": [
    {
      "price": 73.91,
      "volume": 18607278
    },
    {
      "price": 73.91,
      "volume": 18607278
    }
  ],
  "PUMP": [
    {
      "price": 0.001814,
      "volume": 98441993
    },
    {
      "price": 0.001814,
      "volume": 98441993
    }
  ],
  "KCS": [
    {
      "price": 8.09,
      "volume": 20560016
    },
    {
      "price": 8.09,
      "volume": 20560016
    }
  ],
  "JTRSY": [
    {
      "price": 1.098,
      "volume": 0
    },
    {
      "price": 1.098,
      "volume": 0
    }
  ],
  "KAS": [
    {
      "price": 0.03759202,
      "volume": 46659396
    },
    {
      "price": 0.03759202,
      "volume": 46659396
    }
  ],
  "POL": [
    {
      "price": 0.096129,
      "volume": 51335086
    },
    {
      "price": 0.096129,
      "volume": 51335086
    }
  ],
  "EUTBL": [
    {
      "price": 1.21,
      "volume": 0
    },
    {
      "price": 1.21,
      "volume": 0
    }
  ],
  "WLD": [
    {
      "price": 0.306309,
      "volume": 119899854
    },
    {
      "price": 0.306309,
      "volume": 119899854
    }
  ]
}